setup.py
src/digimat/__init__.py
src/digimat.db.egg-info/PKG-INFO
src/digimat.db.egg-info/SOURCES.txt
src/digimat.db.egg-info/dependency_links.txt
src/digimat.db.egg-info/namespace_packages.txt
src/digimat.db.egg-info/not-zip-safe
src/digimat.db.egg-info/requires.txt
src/digimat.db.egg-info/top_level.txt
src/digimat/db/__init__.py
src/digimat/db/dbdigimat.py
src/digimat/db/dbmssql.py