Metadata-Version: 1.1
Name: digimat.db
Version: 0.1.7
Summary: Digimat DB
Home-page: http://www.digimat.ch
Author: Frederic Hess
Author-email: fhess@splust.ch
License: PSF
Platform: UNKNOWN
Classifier: Development Status :: 4 - Beta
Classifier: Programming Language :: Python :: 3
